patiencediff/__init__.py
patiencediff/__main__.py
patiencediff/_patiencediff_py.py
patiencediff/_patiencediff_rs.cpython-314t-x86_64-linux-gnu.so
patiencediff/_patiencediff_rs.pyi
patiencediff/py.typed
patiencediff/test_patiencediff.py
patiencediff-0.2.18.dist-info/METADATA
patiencediff-0.2.18.dist-info/WHEEL
patiencediff-0.2.18.dist-info/entry_points.txt
patiencediff-0.2.18.dist-info/top_level.txt
patiencediff-0.2.18.dist-info/RECORD
patiencediff-0.2.18.dist-info/licenses/AUTHORS
patiencediff-0.2.18.dist-info/licenses/COPYING
