Metadata-Version: 2.4
Name: patiencediff
Version: 0.2.18
Summary: Python implementation of the patiencediff algorithm
Maintainer-email: Breezy Developers <team@breezy-vcs.org>
License-Expression: GPL-2.0-or-later
Project-URL: Homepage, https://www.breezy-vcs.org/
Project-URL: Repository, https://github.com/breezy-team/patiencediff
Classifier: Development Status :: 6 - Mature
Classifier: Programming Language :: Python :: 3.9
Classifier: Programming Language :: Python :: 3.10
Classifier: Programming Language :: Python :: 3.11
Classifier: Programming Language :: Python :: 3.12
Classifier: Programming Language :: Python :: 3.13
Classifier: Programming Language :: Python :: 3.14
Classifier: Programming Language :: Python :: Implementation :: CPython
Classifier: Programming Language :: Python :: Implementation :: PyPy
Classifier: Operating System :: POSIX
Requires-Python: >=3.9
License-File: COPYING
License-File: AUTHORS
Provides-Extra: dev
Requires-Dist: ruff==0.13.2; extra == "dev"
Requires-Dist: mypy>=1.0.0; extra == "dev"
Dynamic: license-file
